valorantClientAPI/__init__.py
valorantClientAPI/client.py
valorantClientAPI/riot_auth.py
valorantClientAPI/response/core_game.py
valorantClientAPI/response/errors.py
valorantClientAPI/response/mmr.py
valorantClientAPI/response/pre_game.py
valorantClientAPI/utils/helper.py
valorantClientAPI/utils/limiter.py
valorantClientAPI-0.2.4.dist-info/LICENSE
valorantClientAPI-0.2.4.dist-info/METADATA
valorantClientAPI-0.2.4.dist-info/WHEEL
valorantClientAPI-0.2.4.dist-info/top_level.txt
valorantClientAPI-0.2.4.dist-info/RECORD
