Metadata-Version: 2.1
Name: valorantClientAPI
Version: 0.2.4
Summary: Asynchronous Python wrapper for VALORANT's Client API 
Home-page: https://github.com/Jet612/VALORANT-Async-Client-API
Author: Jet612
Project-URL: Documentation, https://github.com/Jet612/VALORANT-Async-Client-API/tree/main/docs
Project-URL: Bug Tracker, https://github.com/users/Jet612/projects/8
Classifier: Programming Language :: Python :: 3.8
Classifier: License :: OSI Approved :: MIT License
Classifier: Operating System :: OS Independent
Classifier: Development Status :: 4 - Beta
Requires-Python: >=3.8
License-File: LICENSE
Requires-Dist: aiohttp ==3.8.3
Requires-Dist: dataclass-wizard ==0.22.2
Requires-Dist: requests ==2.28.2
Requires-Dist: setuptools ==65.5.0
